[{"x":"1955","y":2.17},{"x":"1956","y":5.13},{"x":"1957","y":2.13},{"x":"1958","y":2.94},{"x":"1959","y":5.88},{"x":"1960","y":3.23},{"x":"1962","y":2.94},{"x":"1965","y":2.33},{"x":"1966","y":4.08},{"x":"1967","y":1.69},{"x":"1968","y":7.27},{"x":"1969","y":6.67},{"x":"1970","y":12.2},{"x":"1971","y":8},{"x":"1972","y":7.14},{"x":"1973","y":4.08},{"x":"1974","y":3.57},{"x":"1975","y":9.68},{"x":"1976","y":14.29},{"x":"1977","y":8.82},{"x":"1978","y":12},{"x":"1979","y":13.11},{"x":"1980","y":13.33}]